{"id":"zcdgb","label":"","pages":[{"id":"index","title":"Home Page","content":[{"id":"gzlmp","type":"content","value":{"html":""}},{"id":"ipflw","type":"component","symbolID":"rifim","value":{"raw":{"html":"<div class=\"flex justify-between container \">\n    <img class=\"h-24\" src=\"{{logo.url}}\" alt=\"{{logo.alt}}\">\n    <nav class=\" mt-10  \">\n    <ul class=\" flex \">\n        {{#each nav}}\n        <li class=\"flex font-bold  border-3 text-black-500 px-4 py-4  justify-end\">\n          <a href=\"{{url}}\">{{label}}</a>\n        </li>\n        {{/each}}\n        <a class=\" border-2 font-bold text-blue-800   hover:bg-blue-500 text-white px-4 py-4\" href=\"\">FACE BOOK </a>\n    </ul>\n    </nav>\n    \n</div>","css":"","js":"","fields":[{"id":"lflol","key":"logo","label":"logo ","value":{"url":"http://stars-egypt.org/wp-content/uploads/2017/05/stars-egypt-logo@2x.png","alt":"","size":null},"type":"image","fields":[]},{"id":"mnqhx","key":"nav","label":"Navigation Items","value":[{"label":"PROGRAM","url":"/program"},{"label":"GET INVOLVED ","url":"/get-involved"},{"label":"CONTACT ","url":"/contact "},{"label":"DONATE ","url":"/Donate "}],"type":"repeater","fields":[{"id":"skkdk","key":"label","label":"label","value":"","type":"text"},{"id":"jvsxq","key":"url","label":"url","value":"","type":"url"}]},{"id":"jfwvl","key":"label","label":"heading ","value":[],"type":"repeater","fields":[{"id":"xtigj","key":"label","label":"link ","value":"","type":"text"}]}]},"final":{"html":"<div class=\"flex justify-between container \">\n    <img class=\"h-24\" src=\"\" alt=\"\">\n    <nav class=\" mt-10  \">\n    <ul class=\" flex \">\n        <a class=\" border-2 font-bold text-blue-800   hover:bg-blue-500 text-white px-4 py-4\" href=\"\">FACE BOOK </a>\n    </ul>\n    </nav>\n    \n</div>","css":"#component-ipflw {\n}","js":"          const primo = {\n            id: 'ipflw',\n            data: {\"label\":[]},\n            fields: [{\"id\":\"jfwvl\",\"key\":\"label\",\"label\":\"heading \",\"value\":[],\"type\":\"repeater\",\"fields\":[{\"id\":\"xtigj\",\"key\":\"label\",\"label\":\"link \",\"value\":\"\",\"type\":\"text\"}]}]\n          }\n        "}}}],"styles":{"raw":"","final":"","tailwind":"{\n  theme: {\n    container: {\n      center: true,\n      padding: '2rem'\n    }\n  },\n  variants: {}\n}"},"wrapper":{"head":{"raw":"","final":""},"below":{"raw":"","final":""}},"fields":[]}],"styles":{"raw":"/* Default content styles */\n\n.primo-copy {\n  @apply text-lg text-gray-700 container;\n  h1 {\n    @apply text-3xl font-medium;\n  }\n  h2 {\n    @apply text-2xl font-medium;\n  }\n  ol {\n    @apply list-decimal;\n  }\n  ul {\n    @apply list-disc list-inside;\n    p {\n        @apply inline;\n    }\n  } \n  ol {\n    @apply list-decimal list-inside;\n  } \n  a {\n    @apply text-blue-600 underline;\n  }\n  blockquote {\n      @apply shadow-md p-6;\n  }\n  mark {\n    @apply text-gray-900 bg-yellow-200;\n  }\n  \n  @screen lg {\n    h1 {\n      @apply text-5xl;\n    }\n    h2 {\n      @apply text-4xl;\n    }\n  }\n}","final":"/* Default content styles */\n\n.primo-copy {\n  width: 100%;\n  margin-right: auto;\n  margin-left: auto;\n  padding-right: 2rem;\n  padding-left: 2rem\n}\n\n@media (min-width: 640px) {\n  .primo-copy {\n    max-width: 640px\n  }\n}\n\n@media (min-width: 768px) {\n  .primo-copy {\n    max-width: 768px\n  }\n}\n\n@media (min-width: 1024px) {\n  .primo-copy {\n    max-width: 1024px\n  }\n}\n\n@media (min-width: 1280px) {\n  .primo-copy {\n    max-width: 1280px\n  }\n}\n\n@media (min-width: 1536px) {\n  .primo-copy {\n    max-width: 1536px\n  }\n}\n\n.primo-copy {\n  font-size: 1.125rem;\n  --text-opacity: 1;\n  color: #374151;\n  color: rgba(55, 65, 81, var(--text-opacity));\n}\n\n.primo-copy h1 {\n    font-size: 1.875rem;\n    font-weight: 500;\n  }\n\n.primo-copy h2 {\n    font-size: 1.5rem;\n    font-weight: 500;\n  }\n\n.primo-copy ol {\n    list-style-type: decimal;\n  }\n\n.primo-copy ul {\n    list-style-type: disc;\n    list-style-position: inside;\n  }\n\n.primo-copy ul p {\n      display: inline;\n    }\n\n.primo-copy ol {\n    list-style-type: decimal;\n    list-style-position: inside;\n  }\n\n.primo-copy a {\n    --text-opacity: 1;\n    color: #1c64f2;\n    color: rgba(28, 100, 242, var(--text-opacity));\n    text-decoration: underline;\n  }\n\n.primo-copy blockquote {\n    box-shadow: 0 4px 6px -1px rgba(0, 0, 0, 0.1), 0 2px 4px -1px rgba(0, 0, 0, 0.06);\n    padding: 1.5rem;\n  }\n\n.primo-copy mark {\n    --text-opacity: 1;\n    color: #161e2e;\n    color: rgba(22, 30, 46, var(--text-opacity));\n    --bg-opacity: 1;\n    background-color: #fce96a;\n    background-color: rgba(252, 233, 106, var(--bg-opacity));\n  }\n\n@media (min-width: 1024px) {\n  .primo-copy h1 {\n    font-size: 3rem;\n  }\n\n  .primo-copy h2 {\n    font-size: 2.25rem;\n  }\n}\n  ","tailwind":"{\n  theme: {\n    container: {\n      center: true,\n      padding: '2rem'\n    }\n  },\n  variants: {}\n}"},"wrapper":{"head":{"raw":"","final":""},"below":{"raw":"","final":""}},"fields":[],"symbols":[{"type":"symbol","id":"rifim","value":{"raw":{"html":"<div class=\"flex justify-between container \">\n    <img class=\"h-24\" src=\"{{logo.url}}\" alt=\"{{logo.alt}}\">\n    <nav class=\" mt-10  \">\n    <ul class=\" flex \">\n        {{#each nav}}\n        <li class=\"flex font-bold  border-3 text-black-500 px-4 py-4  justify-end\">\n          <a href=\"{{url}}\">{{label}}</a>\n        </li>\n        {{/each}}\n        <a class=\" border-2 font-bold text-blue-800   hover:bg-blue-500 text-white px-4 py-4\" href=\"\">FACE BOOK </a>\n    </ul>\n    </nav>\n    \n</div>","css":"","js":"","fields":[{"id":"lflol","key":"logo","label":"logo ","value":{"url":"http://stars-egypt.org/wp-content/uploads/2017/05/stars-egypt-logo@2x.png","alt":"","size":null},"type":"image","fields":[]},{"id":"mnqhx","key":"nav","label":"Navigation Items","value":[{"label":"PROGRAM","url":"/program"},{"label":"GET INVOLVED ","url":"/get-involved"},{"label":"CONTACT ","url":"/contact "},{"label":"DONATE ","url":"/Donate "}],"type":"repeater","fields":[{"id":"skkdk","key":"label","label":"label","value":"","type":"text"},{"id":"jvsxq","key":"url","label":"url","value":"","type":"url"}]}]},"final":{"html":"<div class=\"flex justify-between container \">\n    <img class=\"h-24\" src=\"http://stars-egypt.org/wp-content/uploads/2017/05/stars-egypt-logo@2x.png\" alt=\"\">\n    <nav class=\" mt-10  \">\n    <ul class=\" flex \">\n        <li class=\"flex font-bold  border-3 text-black-500 px-4 py-4  justify-end\">\n          <a href=\"/program\">PROGRAM</a>\n        </li>\n        <li class=\"flex font-bold  border-3 text-black-500 px-4 py-4  justify-end\">\n          <a href=\"/get-involved\">GET INVOLVED </a>\n        </li>\n        <li class=\"flex font-bold  border-3 text-black-500 px-4 py-4  justify-end\">\n          <a href=\"/contact \">CONTACT </a>\n        </li>\n        <li class=\"flex font-bold  border-3 text-black-500 px-4 py-4  justify-end\">\n          <a href=\"/Donate \">DONATE </a>\n        </li>\n        <a class=\" border-2 font-bold text-blue-800   hover:bg-blue-500 text-white px-4 py-4\" href=\"\">FACE BOOK </a>\n    </ul>\n    </nav>\n    \n</div>","css":"#component-rifim {\n}","js":""}}}]}